<?xml version="1.0" encoding="UTF-8"?>
<preferences>
 <debug showDebugMenu="0" />
 <systemtable filter="All Interfaces">
  <columns>
   <connections preferredWidth="383" />
   <irq preferredWidth="63" />
   <name preferredWidth="210" />
  </columns>
 </systemtable>
 <library
   expandedCategories="Library,Library/Processors and Peripherals,Library/Processors and Peripherals/Inter-Process Communication,Project" />
 <window width="1920" height="1030" x="0" y="0" />
 <generation synthesis="VHDL" block_symbol_file="0" />
 <hdlexample language="VHDL" />
</preferences>
